parksbmi/bmi.py
parksbmi-0.0.0.1.dist-info/METADATA
parksbmi-0.0.0.1.dist-info/WHEEL
parksbmi-0.0.0.1.dist-info/top_level.txt
parksbmi-0.0.0.1.dist-info/RECORD
