Metadata-Version: 2.1
Name: parksbmi
Version: 0.0.0.1
Summary: BMI
Home-page: https://lingua.blog.me/...
Author: Park
Author-email: pdh0184@naver.com
License: MIT
Requires-Python: >=3
